{
  "type": "minecraft:crafting_shaped",
  "result": {
    "item": "congregamystica:drill_head_tipped_void"
  },
  "pattern": [
    "BP ",
    "BHD",
    "BP "
  ],
  "key": {
    "D": {
      "type": "forge:ore_dict",
      "ore": "blockDiamond"
    },
    "B": {
      "type": "forge:ore_dict",
      "ore": "blockVoid"
    },
    "P": {
      "type": "forge:ore_dict",
      "ore": "plateVoid"
    },
    "H": {
      "item": "congregamystica:drill_head_void"
    }
  },
  "conditions": [
    {
      "type": "minecraft:item_exists",
      "item": "congregamystica:drill_head_tipped_void"
    }
  ]
}